varhist.py
varhist-0.0.9.dist-info/LICENSE.txt
varhist-0.0.9.dist-info/METADATA
varhist-0.0.9.dist-info/WHEEL
varhist-0.0.9.dist-info/top_level.txt
varhist-0.0.9.dist-info/RECORD
