Metadata-Version: 2.1
Name: varhist
Version: 0.0.9
Summary: Get Variable History of specific variables
Home-page: https://github.com/Rithwik-G/VarHist-Python-Package
Author: Rithwik Gupta
Author-email: rithwikca2020@gmail.com
License: AGPLv3
Platform: UNKNOWN
Classifier: Programming Language :: Python :: 3
Classifier: Programming Language :: Python :: 2
Classifier: Operating System :: OS Independent
Classifier: License :: OSI Approved :: GNU General Public License v3 (GPLv3)
Provides-Extra: dev
Requires-Dist: pytest (>=3.7) ; extra == 'dev'
Requires-Dist: check-manifest ; extra == 'dev'
